pfrtf.py
pfrtf-0.0.1.dist-info/LICENSE
pfrtf-0.0.1.dist-info/METADATA
pfrtf-0.0.1.dist-info/WHEEL
pfrtf-0.0.1.dist-info/top_level.txt
pfrtf-0.0.1.dist-info/RECORD
