Metadata-Version: 2.1
Name: pfrtf
Version: 0.0.1
Summary: Pandas fast reading table file by using pickle
Author-email: Artem Grigorev <ofyenn@gmail.com>
Project-URL: Homepage, https://github.com/ofyenn/pandas_quick_table_rereading
Project-URL: Bug Tracker, https://github.com/ofyenn/pandas_quick_table_rereading/issues
Classifier: Programming Language :: Python :: 3
Classifier: License :: OSI Approved :: MIT License
Requires-Python: >=3.7
License-File: LICENSE
Requires-Dist: Pandas (>=1.4.4)
Requires-Dist: openpyxl (>=2.6.0)
